pycosmommf/__init__.py
pycosmommf/_version.py
pycosmommf/_version.pyi
pycosmommf/filter.py
pycosmommf/hessian.py
pycosmommf/py.typed
pycosmommf/signatures.py
pycosmommf/tagging.py
pycosmommf/utils.py
pycosmommf-1.0.3.dist-info/METADATA
pycosmommf-1.0.3.dist-info/WHEEL
pycosmommf-1.0.3.dist-info/licenses/LICENSE
pycosmommf-1.0.3.dist-info/RECORD
