Metadata-Version: 2.4
Name: pycosmommf
Version: 1.0.3
Summary: A package for identifying structures in the cosmic web.
Project-URL: Homepage, https://github.com/James11222/pycosmommf
Project-URL: Bug Tracker, https://github.com/James11222/pycosmommf/issues
Project-URL: Discussions, https://github.com/James11222/pycosmommf/discussions
Project-URL: Changelog, https://github.com/James11222/pycosmommf/releases
Author-email: James Sunseri <js7501@princeton.edu>
License: Copyright 2024 James Sunseri
License-File: LICENSE
Classifier: Development Status :: 1 - Planning
Classifier: Intended Audience :: Developers
Classifier: Intended Audience :: Science/Research
Classifier: License :: OSI Approved :: MIT License
Classifier: Operating System :: OS Independent
Classifier: Programming Language :: Python
Classifier: Programming Language :: Python :: 3
Classifier: Programming Language :: Python :: 3 :: Only
Classifier: Programming Language :: Python :: 3.8
Classifier: Programming Language :: Python :: 3.9
Classifier: Programming Language :: Python :: 3.10
Classifier: Programming Language :: Python :: 3.11
Classifier: Programming Language :: Python :: 3.12
Classifier: Topic :: Scientific/Engineering
Classifier: Typing :: Typed
Requires-Python: <3.13,>=3.8
Requires-Dist: numba
Requires-Dist: numpy>=1.22
Requires-Dist: scikit-image
Provides-Extra: dev
Requires-Dist: pytest-cov>=3; extra == 'dev'
Requires-Dist: pytest>=6; extra == 'dev'
Provides-Extra: docs
Requires-Dist: furo>=2023.08.17; extra == 'docs'
Requires-Dist: myst-parser>=0.13; extra == 'docs'
Requires-Dist: sphinx-autodoc-typehints; extra == 'docs'
Requires-Dist: sphinx-copybutton; extra == 'docs'
Requires-Dist: sphinx>=7.0; extra == 'docs'
Provides-Extra: test
Requires-Dist: pytest-cov>=3; extra == 'test'
Requires-Dist: pytest>=6; extra == 'test'
